acestream_search/__init__.py
acestream_search/_version.py
acestream_search/acestream_search.py
acestream_search-1.6.4.dist-info/licenses/LICENSE
acestream_search-1.6.4.dist-info/METADATA
acestream_search-1.6.4.dist-info/WHEEL
acestream_search-1.6.4.dist-info/entry_points.txt
acestream_search-1.6.4.dist-info/top_level.txt
acestream_search-1.6.4.dist-info/RECORD
